{
    "replace": true,
    "slots": [
        "shield/plate"
    ],
    "materialSlotCount": 1,
    "displayType": "major",
    "glyph": {
        "textureX": 48,
        "textureY": 48
    },
    "outcomes": [
        {
            "material": {
                "item": "minecraft:oak_planks"
            },
            "requiredTools": {
                "axe": 1
            },
            "moduleKey": "shield/buckler",
            "moduleVariant": "buckler/wooden"
        },
        {
            "material": {
                "item": "minecraft:bone"
            },
            "moduleKey": "shield/buckler",
            "moduleVariant": "buckler/bone"
        },
        {
            "material": {
                "item": "minecraft:iron_ingot"
            },
            "requiredTools": {
                "hammer": 2
            },
            "moduleKey": "shield/buckler",
            "moduleVariant": "buckler/iron"
        },

        {
            "material": {
                "item": "minecraft:gold_ingot"
            },
            "requiredTools": {
                "hammer": 2
            },
            "moduleKey": "shield/buckler",
            "moduleVariant": "buckler/gold"
        },
        {
            "material": {
                "tag": "forge:ingots/copper"
            },
            "requiredTools": {
                "hammer": 3
            },
            "moduleKey": "shield/buckler",
            "moduleVariant": "buckler/copper"
        },
        {
            "material": {
                "tag": "forge:ingots/tin"
            },
            "requiredTools": {
                "hammer": 2
            },
            "moduleKey": "shield/buckler",
            "moduleVariant": "buckler/tin"
        },
        {
            "material": {
                "tag": "forge:ingots/silver"
            },
            "requiredTools": {
                "hammer": 2
            },
            "moduleKey": "shield/buckler",
            "moduleVariant": "buckler/silver"
        },
        {
            "material": {
                "tag": "forge:ingots/nickel"
            },
            "requiredTools": {
                "hammer": 3
            },
            "moduleKey": "shield/buckler",
            "moduleVariant": "buckler/nickel"
        },
        {
            "material": {
                "tag": "forge:ingots/lead"
            },
            "requiredTools": {
                "hammer": 3
            },
            "moduleKey": "shield/buckler",
            "moduleVariant": "buckler/lead"
        },
        {
            "material": {
                "tag": "forge:ingots/electrum"
            },
            "requiredTools": {
                "hammer": 3
            },
            "moduleKey": "shield/buckler",
            "moduleVariant": "buckler/electrum"
        },
        {
            "material": {
                "tag": "forge:ingots/bronze"
            },
            "requiredTools": {
                "hammer": 2
            },
            "moduleKey": "shield/buckler",
            "moduleVariant": "buckler/bronze"
        },
        {
            "material": {
                "tag": "forge:ingots/steel"
            },
            "requiredTools": {
                "hammer": 4
            },
            "moduleKey": "shield/buckler",
            "moduleVariant": "buckler/steel"
        },
        {
            "material": {
                "item": "minecraft:spruce_planks"
            },
            "requiredTools": {
                "axe": 1
            },
            "moduleKey": "shield/buckler",
            "moduleVariant": "buckler/spruce"
        },
        {
            "material": {
                "item": "minecraft:birch_planks"
            },
            "requiredTools": {
                "axe": 1
            },
            "moduleKey": "shield/buckler",
            "moduleVariant": "buckler/birch"
        },
        {
            "material": {
                "item": "minecraft:jungle_planks"
            },
            "requiredTools": {
                "axe": 1
            },
            "moduleKey": "shield/buckler",
            "moduleVariant": "buckler/jungle"
        },
        {
            "material": {
                "item": "minecraft:acacia_planks"
            },
            "requiredTools": {
                "axe": 1
            },
            "moduleKey": "shield/buckler",
            "moduleVariant": "buckler/acacia"
        },
        {
            "material": {
                "item": "minecraft:dark_oak_planks"
            },
            "requiredTools": {
                "axe": 1
            },
            "moduleKey": "shield/buckler",
            "moduleVariant": "buckler/dark_oak"
        },
        {
            "material": {
                "tag": "forge:planks/maple"
            },
            "requiredTools": {
                "axe": 2
            },
            "moduleKey": "shield/buckler",
            "moduleVariant": "buckler/maple"
        },
        {
            "material": {
                "tag": "forge:planks/cherry"
            },
            "requiredTools": {
                "axe": 3
            },
            "moduleKey": "shield/buckler",
            "moduleVariant": "buckler/cherry"
        },
        {
            "material": {
                "tag": "forge:planks/baobab"
            },
            "requiredTools": {
                "axe": 3
            },
            "moduleKey": "shield/buckler",
            "moduleVariant": "buckler/baobab"
        },
        {
            "material": {
                "item": "tetra:vent_plate",
                "count": 2
            },
            "requiredTools": {
                "hammer": 4
            },
            "moduleKey": "shield/buckler",
            "moduleVariant": "buckler/vent"
        }
    ]
}