{
    "replace": true,
    "type": "tetra:multi_major_module",
    "slots": [
        "double/head_right"
    ],
    "slotSuffixes": [
        "_right"
    ],
    "improvements": [
        "tetra:double/butt/",
        "tetra:double/shared_head/",
        "tetra:double/shared/",
        "tetra:shared/"
    ],
    "variants": [
        {
            "materials": [ "tetra:metal/", "tetra:stone/", "tetra:wood/", "tetra:gem/" ],
            "key": "butt/",
            "attributes": {
                "generic.attack_speed": -1
            },
            "aspects": {
                "blockBreaker": 1,
                "breakable": 2
            },
            "durability": -10,
            "extract": {
                "durability": 0.5,
                "integrity": -0.5,
                "magicCapacity": 1,
                "glyph": {
                    "textureX": 160
                },
                "availableTextures": [ "crude", "metal", "shiny" ],
                "models": [ { "location": "tetra:items/module/double/head/butt/" } ]
            }
        }
    ]
}
