[
    {
        "modules": ["double/basic_hammer", "double/basic_axe"],
        "name": "double/axe_hammer"
    },
    {
        "modules": ["double/basic_axe", "double/basic_axe"],
        "name": "double/axe_axe",
        "damageMultiplier": 1.2,
        "attackSpeedMultiplier": 0.9
    },
    {
        "modules": ["double/basic_axe", "double/basic_pickaxe"],
        "name": "double/axe_pickaxe"
    },
    {
        "modules": ["double/basic_hammer", "double/basic_pickaxe"],
        "name": "double/hammer_pickaxe"
    },
    {
        "modules": ["double/adze", "double/basic_pickaxe"],
        "name": "double/adze_pickaxe"
    },
    {
        "modules": ["double/adze", "double/basic_axe"],
        "name": "double/adze_axe"
    },
    {
        "modules": ["double/claw", "double/basic_hammer"],
        "name": "double/claw_hammer"
    },
    {
        "modules": ["double/claw", "double/basic_axe"],
        "name": "double/claw_axe"
    },
    {
        "modules": ["double/basic_pickaxe", "double/basic_pickaxe"],
        "sameVariant": true,
        "capabilities": {
            "pickaxe": 1
        }
    },
    {
        "moduleVariants": ["basic_hammer/stone", "basic_hammer/stone"],
        "capabilities": {
            "hammer": 1
        }
    },
    {
        "moduleVariants": ["basic_hammer/iron", "basic_hammer/iron"],
        "damage": 1,
        "capabilities": {
            "hammer": 1
        }
    },
    {
        "moduleVariants": ["basic_hammer/copper", "basic_hammer/copper"],
        "integrity": 1
    },
    {
        "moduleVariants": ["basic_hammer/tin", "basic_hammer/tin"],
        "integrity": 1,
        "capabilities": {
            "hammer": 1
        }
    },
    {
        "moduleVariants": ["basic_hammer/lead", "basic_hammer/lead"],
        "capabilities": {
            "hammer": 1
        }
    },
    {
        "moduleVariants": ["basic_hammer/electrum", "basic_hammer/electrum"],
        "capabilities": {
            "hammer": 1
        }
    },
    {
        "moduleVariants": ["basic_hammer/thaumium", "basic_hammer/thaumium"],
        "capabilities": {
            "hammer": 1
        }
    },
    {
        "moduleVariants": ["basic_hammer/ironwood", "basic_hammer/ironwood"],
        "capabilities": {
            "hammer": 1
        }
    },
    {
        "moduleVariants": ["basic_hammer/fierymetal", "basic_hammer/fierymetal"],
        "capabilities": {
            "hammer": 1
        }
    }
]