[
    {
        "modules": ["duplex/basic_hammer", "duplex/basic_axe"],
        "name": "duplex/axe_hammer"
    },
    {
        "modules": ["duplex/basic_axe", "duplex/basic_axe"],
        "name": "duplex/axe_axe",
        "damageMultiplier": 1.2,
        "attackSpeedMultiplier": 0.9
    },
    {
        "modules": ["duplex/basic_axe", "duplex/basic_pickaxe"],
        "name": "duplex/axe_pickaxe"
    },
    {
        "modules": ["duplex/basic_hammer", "duplex/basic_pickaxe"],
        "name": "duplex/hammer_pickaxe"
    },
    {
        "modules": ["duplex/adze", "duplex/basic_pickaxe"],
        "name": "duplex/adze_pickaxe"
    },
    {
        "modules": ["duplex/adze", "duplex/basic_axe"],
        "name": "duplex/adze_axe"
    },
    {
        "modules": ["duplex/claw", "duplex/basic_hammer"],
        "name": "duplex/claw_hammer"
    },
    {
        "modules": ["duplex/claw", "duplex/basic_axe"],
        "name": "duplex/claw_axe"
    },
    {
        "moduleVariants": ["basic_hammer/stone", "basic_hammer/stone"],
        "capabilities": {
            "hammer": 1
        }
    },
    {
        "moduleVariants": ["basic_hammer/iron", "basic_hammer/iron"],
        "damage": 1,
        "capabilities": {
            "hammer": 1
        }
    },
    {
        "moduleVariants": ["basic_hammer/copper", "basic_hammer/copper"],
        "integrity": 1
    },
    {
        "moduleVariants": ["basic_hammer/tin", "basic_hammer/tin"],
        "integrity": 1,
        "capabilities": {
            "hammer": 1
        }
    },
    {
        "moduleVariants": ["basic_hammer/lead", "basic_hammer/lead"],
        "capabilities": {
            "hammer": 1
        }
    },
    {
        "moduleVariants": ["basic_hammer/obsidian", "basic_hammer/obsidian"],
        "capabilities": {
            "hammer": 1
        }
    },
    {
        "moduleVariants": ["basic_hammer/electrum", "basic_hammer/electrum"],
        "capabilities": {
            "hammer": 1
        }
    },
    {
        "moduleVariants": ["basic_hammer/thaumium", "basic_hammer/thaumium"],
        "capabilities": {
            "hammer": 1
        }
    },
    {
        "moduleVariants": ["basic_hammer/ironwood", "basic_hammer/ironwood"],
        "capabilities": {
            "hammer": 1
        }
    },
    {
        "moduleVariants": ["basic_hammer/fierymetal", "basic_hammer/fierymetal"],
        "capabilities": {
            "hammer": 1
        }
    },
    {
        "moduleVariants": ["basic_pickaxe/cobblestone", "basic_pickaxe/cobblestone"],
        "capabilities": {
            "pickaxe": 1
        }
    },
    {
        "moduleVariants": ["basic_pickaxe/steel", "basic_pickaxe/steel"],
        "capabilities": {
            "pickaxe": 1
        }
    },
    {
        "moduleVariants": ["basic_pickaxe/steeleaf", "basic_pickaxe/steeleaf"],
        "capabilities": {
            "pickaxe": 1
        }
    },
    {
        "moduleVariants": ["basic_pickaxe/fierymetal", "basic_pickaxe/fierymetal"],
        "capabilities": {
            "pickaxe": 1
        }
    }
]