{
    "replace": true,
    "slots": [
        "sword/pommel"
    ],
    "materialSlotCount": 1,
    "displayType": "minor",
    "glyph": {
        "textureX": 32,
        "textureY": 16
    },
    "outcomes": [
        {
            "material": {
                "item": "minecraft:spruce_planks"
            },
            "requiredTools": {
                "axe": 1
            },
            "moduleKey": "sword/counterweight",
            "moduleVariant": "counterweight/spruce"
        },
        {
            "material": {
                "item": "minecraft:birch_planks"
            },
            "requiredTools": {
                "axe": 1
            },
            "moduleKey": "sword/counterweight",
            "moduleVariant": "counterweight/birch"
        },
        {
            "material": {
                "item": "minecraft:jungle_planks"
            },
            "requiredTools": {
                "axe": 1
            },
            "moduleKey": "sword/counterweight",
            "moduleVariant": "counterweight/jungle"
        },
        {
            "material": {
                "item": "minecraft:acacia_planks"
            },
            "requiredTools": {
                "axe": 1
            },
            "moduleKey": "sword/counterweight",
            "moduleVariant": "counterweight/acacia"
        },
        {
            "material": {
                "item": "minecraft:dark_oak_planks"
            },
            "requiredTools": {
                "axe": 1
            },
            "moduleKey": "sword/counterweight",
            "moduleVariant": "counterweight/dark_oak"
        },
        {
            "material": {
                "item": "minecraft:granite"
            },
            "requiredTools": {
                "hammer": 2
            },
            "moduleKey": "sword/counterweight",
            "moduleVariant": "counterweight/granite"
        },
        {
            "material": {
                "item": "minecraft:diorite"
            },
            "requiredTools": {
                "hammer": 1
            },
            "moduleKey": "sword/counterweight",
            "moduleVariant": "counterweight/diorite"
        },
        {
            "material": {
                "item": "minecraft:andesite"
            },
            "requiredTools": {
                "hammer": 2
            },
            "moduleKey": "sword/counterweight",
            "moduleVariant": "counterweight/andesite"
        },
        {
            "material": {
                "item": "minecraft:iron_ingot"
            },
            "requiredTools": {
                "hammer": 1
            },
            "moduleKey": "sword/counterweight",
            "moduleVariant": "counterweight/iron"
        },
        {
            "material": {
                "item": "minecraft:flint"
            },
            "requiredTools": {
                "hammer": 1
            },
            "moduleKey": "sword/counterweight",
            "moduleVariant": "counterweight/flint"
        },
        {
            "material": {
                "item": "minecraft:gold_ingot"
            },
            "requiredTools": {
                "hammer": 1
            },
            "moduleKey": "sword/counterweight",
            "moduleVariant": "counterweight/gold"
        },
        {
            "material": {
                "item": "minecraft:diamond"
            },
            "requiredTools": {
                "hammer": 1
            },
            "moduleKey": "sword/counterweight",
            "moduleVariant": "counterweight/diamond"
        },
        {
            "material": {
                "item": "minecraft:obsidian"
            },
            "requiredTools": {
                "hammer": 3
            },
            "moduleKey": "sword/counterweight",
            "moduleVariant": "counterweight/obsidian"
        },
        {
            "material": {
                "tag": "forge:ingots/copper"
            },
            "requiredTools": {
                "hammer": 2
            },
            "moduleKey": "sword/counterweight",
            "moduleVariant": "counterweight/copper"
        },
        {
            "material": {
                "tag": "forge:ingots/tin"
            },
            "requiredTools": {
                "hammer": 2
            },
            "moduleKey": "sword/counterweight",
            "moduleVariant": "counterweight/tin"
        },
        {
            "material": {
                "tag": "forge:ingots/silver"
            },
            "requiredTools": {
                "hammer": 2
            },
            "moduleKey": "sword/counterweight",
            "moduleVariant": "counterweight/silver"
        },
        {
            "material": {
                "tag": "forge:ingots/nickel"
            },
            "requiredTools": {
                "hammer": 2
            },
            "moduleKey": "sword/counterweight",
            "moduleVariant": "counterweight/nickel"
        },
        {
            "material": {
                "tag": "forge:ingots/lead"
            },
            "requiredTools": {
                "hammer": 2
            },
            "moduleKey": "sword/counterweight",
            "moduleVariant": "counterweight/lead"
        },
        {
            "material": {
                "tag": "forge:ingots/bronze"
            },
            "requiredTools": {
                "hammer": 2
            },
            "moduleKey": "sword/counterweight",
            "moduleVariant": "counterweight/bronze"
        },
        {
            "material": {
                "tag": "forge:ingots/electrum"
            },
            "requiredTools": {
                "hammer": 2
            },
            "moduleKey": "sword/counterweight",
            "moduleVariant": "counterweight/electrum"
        },
        {
            "material": {
                "tag": "forge:ingots/steel"
            },
            "requiredTools": {
                "hammer": 2
            },
            "moduleKey": "sword/counterweight",
            "moduleVariant": "counterweight/steel"
        },
        {
            "material": {
                "tag": "forge:ingots/ironwood"
            },
            "requiredTools": {
                "hammer": 2
            },
            "moduleKey": "sword/counterweight",
            "moduleVariant": "counterweight/ironwood"
        },
        {
            "material": {
                "tag": "forge:ingots/steeleaf"
            },
            "requiredTools": {
                "hammer": 2
            },
            "moduleKey": "sword/counterweight",
            "moduleVariant": "counterweight/steeleaf"
        },
        {
            "material": {
                "tag": "forge:ingots/fiery"
            },
            "requiredTools": {
                "hammer": 2
            },
            "moduleKey": "sword/counterweight",
            "moduleVariant": "counterweight/fierymetal"
        },
        {
            "material": {
                "tag": "forge:ingots/knightmetal"
            },
            "requiredTools": {
                "hammer": 2
            },
            "moduleKey": "sword/counterweight",
            "moduleVariant": "counterweight/knightmetal"
        },
        {
            "material": {
                "tag": "minecraft:planks"
            },
            "requiredTools": {
                "axe": 1
            },
            "moduleKey": "sword/counterweight",
            "moduleVariant": "counterweight/oak"
        },
        {
            "material": {
                "tag": "forge:cobblestone"
            },
            "requiredTools": {
                "hammer": 1
            },
            "moduleKey": "sword/counterweight",
            "moduleVariant": "counterweight/cobblestone"
        },
        {
            "material": {
                "tag": "forge:stone"
            },
            "requiredTools": {
                "hammer": 2
            },
            "moduleKey": "sword/counterweight",
            "moduleVariant": "counterweight/stone"
        }
    ]
}